__init__.py
ini.py
pelicandb.py
samples_pelican.py
samples_pelican_ru.py
pelicandbms-0.5.70.dist-info/LICENSE
pelicandbms-0.5.70.dist-info/METADATA
pelicandbms-0.5.70.dist-info/WHEEL
pelicandbms-0.5.70.dist-info/top_level.txt
pelicandbms-0.5.70.dist-info/RECORD
