Metadata-Version: 2.2
Name: pelicandbms
Version: 0.5.70
Summary: Ultrafast binary JSON-oriented NoSQL
Author-email: Dmitry Vorontsov <dv1555@hotmail.com>
Classifier: Programming Language :: Python :: 3
Classifier: License :: OSI Approved :: GNU General Public License v3 or later (GPLv3+)
Classifier: Operating System :: OS Independent
Requires-Python: >=3.7
License-File: LICENSE
Requires-Dist: filelock
